[{"IdOT":38,"FechaOT":"2018-04-17 12:25:00","Resumen":"REGULADOR - NO ENCIENDE, CON NUMERO DE INVENTARIO \n130-43-6-086","Peso":7,"NombreUnidad":"FAMILIA","FechaResolucion":"2018-05-24 16:34:24","NombreActivoFijo":"SIN SELECCIONAR","Dispositivo":"SIN SELECCIONAR","NombrePrioridad":"Normal","IdEstado":4,"CodigoTecnico":"MALOPEZR"},{"IdOT":106,"FechaOT":"2018-05-09 11:05:00","Resumen":"MONITOR - DESCARGO","Peso":9,"NombreUnidad":"DEFENSORIA PUBLICA","FechaResolucion":"2018-05-17 09:47:49","NombreActivoFijo":"COMPUTADORA COMPLETA","Dispositivo":"SIN SELECCIONAR","NombrePrioridad":"Normal","IdEstado":4,"CodigoTecnico":"LFMONGER"},{"IdOT":107,"FechaOT":"2018-05-09 11:08:00","Resumen":"TECLADO - DESCARGO","Peso":8,"NombreUnidad":"DEFENSORIA PUBLICA","FechaResolucion":"2018-06-19 11:44:31","NombreActivoFijo":"COMPUTADORA COMPLETA","Dispositivo":"SIN SELECCIONAR","NombrePrioridad":"Normal","IdEstado":4,"CodigoTecnico":"JAMURILLOJ"},{"IdOT":134,"FechaOT":"2018-05-21 09:48:00","Resumen":"CPU - DESCARGO","Peso":8,"NombreUnidad":"DEFENSORIA PUBLICA","FechaResolucion":"2018-06-19 09:03:57","NombreActivoFijo":"COMPUTADORA COMPLETA","Dispositivo":"SIN SELECCIONAR","NombrePrioridad":"Normal","IdEstado":4,"CodigoTecnico":"RALOPEZH"},{"IdOT":137,"FechaOT":"2018-05-21 10:59:00","Resumen":"CPU - DESCARGO","Peso":8,"NombreUnidad":"DEFENSORIA PUBLICA","FechaResolucion":"2018-05-28 12:19:35","NombreActivoFijo":"COMPUTADORA COMPLETA","Dispositivo":"SIN SELECCIONAR","NombrePrioridad":"Normal","IdEstado":4,"CodigoTecnico":"RALOPEZH"},{"IdOT":140,"FechaOT":"2018-05-21 14:13:00","Resumen":"TECLADO -DESCARGO","Peso":3,"NombreUnidad":"DEFENSORIA PUBLICA","FechaResolucion":"2018-05-28 14:34:52","NombreActivoFijo":"COMPUTADORA COMPLETA","Dispositivo":"SIN SELECCIONAR","NombrePrioridad":"Normal","IdEstado":4,"CodigoTecnico":"RALOPEZH"},{"IdOT":141,"FechaOT":"2018-05-21 14:20:00","Resumen":"TECLADO - DESCARGO","Peso":3,"NombreUnidad":"DEFENSORIA PUBLICA","FechaResolucion":"2018-05-28 14:34:22","NombreActivoFijo":"COMPUTADORA COMPLETA","Dispositivo":"SIN SELECCIONAR","NombrePrioridad":"Normal","IdEstado":4,"CodigoTecnico":"RALOPEZH"},{"IdOT":146,"FechaOT":"2018-05-22 09:10:00","Resumen":"CPU - DESCARGO","Peso":8,"NombreUnidad":"COORD. NAC. DE MEDIACION","FechaResolucion":"2018-06-12 14:52:05","NombreActivoFijo":"C P U Y MONITOR","Dispositivo":"SIN SELECCIONAR","NombrePrioridad":"Normal","IdEstado":4,"CodigoTecnico":"MALOPEZR"},{"IdOT":147,"FechaOT":"2018-05-22 09:14:00","Resumen":"MONITOR - DESCARGO","Peso":9,"NombreUnidad":"COORD. NAC. DE MEDIACION","FechaResolucion":"2018-05-29 11:00:00","NombreActivoFijo":"C P U Y MONITOR","Dispositivo":"SIN SELECCIONAR","NombrePrioridad":"Normal","IdEstado":4,"CodigoTecnico":"MALOPEZR"},{"IdOT":152,"FechaOT":"2018-05-23 15:01:00","Resumen":"UPS - DESCARGO","Peso":7,"NombreUnidad":"PROCURADOR(A) AUXILIAR SANTA TECLA (PA13)","FechaResolucion":"2018-05-28 16:00:00","NombreActivoFijo":"COMPUTADORA COMPLETA","Dispositivo":"SIN SELECCIONAR","NombrePrioridad":"Normal","IdEstado":4,"CodigoTecnico":"MALOPEZR"},{"IdOT":191,"FechaOT":"2018-06-06 08:55:00","Resumen":"UPS - PARA DESCARGO","Peso":7,"NombreUnidad":"PROCURADOR(A) AUXILIAR APOPA (PA15)","FechaResolucion":"2018-06-19 09:55:16","NombreActivoFijo":"UPS","Dispositivo":"SIN SELECCIONAR","NombrePrioridad":"Normal","IdEstado":4,"CodigoTecnico":"MALOPEZR"},{"IdOT":208,"FechaOT":"2018-06-07 15:01:00","Resumen":"MONITOR -PARA DESCARGO","Peso":9,"NombreUnidad":"UNIDAD DE RECURSOS HUMANOS (RRHH)","FechaResolucion":"2018-06-18 08:26:37","NombreActivoFijo":"COMPUTADORA COMPLETA","Dispositivo":"SIN SELECCIONAR","NombrePrioridad":"Normal","IdEstado":4,"CodigoTecnico":"LFMONGER"},{"IdOT":209,"FechaOT":"2018-06-07 15:03:00","Resumen":"TECLADO - PARA DESCARGO","Peso":3,"NombreUnidad":"UNIDAD DE RECURSOS HUMANOS (RRHH)","FechaResolucion":"2018-06-13 10:44:55","NombreActivoFijo":"COMPUTADORA COMPLETA","Dispositivo":"SIN SELECCIONAR","NombrePrioridad":"Normal","IdEstado":4,"CodigoTecnico":"RALOPEZH"},{"IdOT":210,"FechaOT":"2018-06-07 15:05:00","Resumen":"TECLADO - PARA DESCARGO","Peso":3,"NombreUnidad":"UNIDAD DE RECURSOS HUMANOS (RRHH)","FechaResolucion":"2018-06-13 10:44:05","NombreActivoFijo":"COMPUTADORA COMPLETA","Dispositivo":"SIN SELECCIONAR","NombrePrioridad":"Normal","IdEstado":4,"CodigoTecnico":"RALOPEZH"},{"IdOT":220,"FechaOT":"2018-06-13 08:43:00","Resumen":"SCANER - PARA DESCARGO","Peso":6,"NombreUnidad":"PROCURADOR(A) AUXILIAR ZACATECOLUCA (PA05)","FechaResolucion":"2018-06-19 10:10:11","NombreActivoFijo":"SCANNER","Dispositivo":"SIN SELECCIONAR","NombrePrioridad":"Normal","IdEstado":4,"CodigoTecnico":"JAMURILLOJ"},{"IdOT":223,"FechaOT":"2018-06-13 08:53:00","Resumen":"1800-61104-406-1-0035 \nPARA DESCARGO","Peso":5,"NombreUnidad":"PROCURADOR(A) AUXILIAR ZACATECOLUCA (PA05)","FechaResolucion":"2018-06-19 09:56:33","NombreActivoFijo":"SIN SELECCIONAR","Dispositivo":"SIN SELECCIONAR","NombrePrioridad":"Normal","IdEstado":4,"CodigoTecnico":"MALOPEZR"}]